m_yolo/CT_data.py
m_yolo/__init__.py
m_yolo/data.yaml
m_yolo/generate_yaml.py
m_yolo/label_names.xlsx
m_yolo/nii_rgb.py
m_yolo/nii_to_2d.py
m_yolo/post_process.py
m_yolo/predict_yolo.py
m_yolo/preprocess.py
m_yolo/result.py
m_yolo/sam_pred.py
m_yolo/tiff_to_txt.py
m_yolo/tifffile_text.py
med_yolo-1.0.0.dist-info/licenses/LICENSE
med_yolo-1.0.0.dist-info/METADATA
med_yolo-1.0.0.dist-info/WHEEL
med_yolo-1.0.0.dist-info/entry_points.txt
med_yolo-1.0.0.dist-info/top_level.txt
med_yolo-1.0.0.dist-info/RECORD
