Metadata-Version: 2.4
Name: med-yolo
Version: 1.0.0
Summary: Medical Image segmentation with YOLO
Home-page: https://github.com/sumit-ai-ml/MED-YOLO
Author: Sumit Pandey
Author-email: Sumit Pandey <supa@di.ku.dk>
License-Expression: MIT
Project-URL: Homepage, https://github.com/sumit-ai-ml/MED-YOLO
Project-URL: Documentation, https://github.com/sumit-ai-ml/MED-YOLO/wiki
Project-URL: Repository, https://github.com/sumit-ai-ml/MED-YOLO.git
Project-URL: Issues, https://github.com/sumit-ai-ml/MED-YOLO/issues
Classifier: Development Status :: 4 - Beta
Classifier: Intended Audience :: Healthcare Industry
Classifier: Intended Audience :: Science/Research
Classifier: Programming Language :: Python :: 3
Classifier: Programming Language :: Python :: 3.11
Classifier: Topic :: Scientific/Engineering :: Medical Science Apps.
Requires-Python: >=3.11
License-File: LICENSE
Requires-Dist: streamlit>=1.24.0
Requires-Dist: torch>=2.0.0
Requires-Dist: torchvision>=0.15.0
Requires-Dist: ultralytics>=8.0.0
Requires-Dist: opencv-python>=4.7.0
Requires-Dist: numpy>=1.24.0
Requires-Dist: pandas>=2.0.0
Requires-Dist: scikit-learn>=1.2.0
Requires-Dist: tifffile>=2023.0.0
Requires-Dist: pillow>=9.5.0
Requires-Dist: matplotlib>=3.7.0
Requires-Dist: seaborn>=0.12.0
Requires-Dist: nibabel>=5.1.0
Requires-Dist: SimpleITK>=2.2.0
Requires-Dist: pydicom>=2.4.0
Requires-Dist: monai>=1.2.0
Requires-Dist: albumentations>=1.3.0
Requires-Dist: PyYAML>=6.0.0
Requires-Dist: requests>=2.31.0
Dynamic: author
Dynamic: home-page
Dynamic: license-file
Dynamic: requires-python
